[
  { "id": "1", "misol": "15*8+3+10", "javob": "133", "false1": "124", "false2": "123", "reward": { "amount": 19, "type": "coin" } },
  { "id": "2", "misol": "18*3+10+1", "javob": "65", "false1": "67", "false2": "73", "reward": { "amount": 10, "type": "coin" } },
  { "id": "3", "misol": "17*3+3+5", "javob": "59", "false1": "57", "false2": "58", "reward": { "amount": 16, "type": "coin" } },
  { "id": "4", "misol": "8*3+4+5", "javob": "33", "false1": "40", "false2": "41", "reward": { "amount": 10, "type": "coin" } },
  { "id": "5", "misol": "15*2+7+1", "javob": "38", "false1": "37", "false2": "42", "reward": { "amount": 13, "type": "coin" } },
  { "id": "6", "misol": "5*5+14+10", "javob": "49", "false1": "55", "false2": "54", "reward": { "amount": 16, "type": "coin" } },
  { "id": "7", "misol": "19*6+8+3", "javob": "125", "false1": "127", "false2": "128", "reward": { "amount": 19, "type": "coin" } },
  { "id": "8", "misol": "13*8+12+3", "javob": "180", "false1": "87", "false2": "73", "reward": { "amount": 150, "type": "coin" } },
  { "id": "9", "misol": "8*5+2+9", "javob": "51", "false1": "54", "false2": "53", "reward": { "amount": 18, "type": "coin" } },
  { "id": "10", "misol": "11*8+9+9", "javob": "106", "false1": "98", "false2": "102", "reward": { "amount": 30, "type": "coin" } },
  { "id": "11", "misol": "20*2+10+1", "javob": "51", "false1": "45", "false2": "60", "reward": { "amount": 27, "type": "coin" } },
  { "id": "12", "misol": "17*6+15+2", "javob": "119", "false1": "122", "false2": "118", "reward": { "amount": 30, "type": "coin" } },
  { "id": "13", "misol": "9*5+3+8", "javob": "56", "false1": "59", "false2": "54", "reward": { "amount": 16, "type": "coin" } },
  { "id": "14", "misol": "19*6+11+4", "javob": "129", "false1": "133", "false2": "134", "reward": { "amount": 19, "type": "coin" } },
  { "id": "15", "misol": "10*8+12+3", "javob": "95", "false1": "105", "false2": "104", "reward": { "amount": 16, "type": "coin" } },
  { "id": "16", "misol": "9*2+13+7", "javob": "38", "false1": "32", "false2": "39", "reward": { "amount": 15, "type": "coin" } },
  { "id": "17", "misol": "18*3+8+10", "javob": "72", "false1": "76", "false2": "82", "reward": { "amount": 24, "type": "coin" } },
  { "id": "18", "misol": "5*7+13+5", "javob": "53", "false1": "47", "false2": "49", "reward": { "amount": 18, "type": "coin" } },
  { "id": "19", "misol": "8*3+1+1", "javob": "26", "false1": "22", "false2": "30", "reward": { "amount": 25, "type": "coin" } },
  { "id": "20", "misol": "11*2+9+3", "javob": "34", "false1": "38", "false2": "40", "reward": { "amount": 18, "type": "coin" } },
  { "id": "21", "misol": "14*10+1+1", "javob": "142", "false1": "135", "false2": "140", "reward": { "amount": 16, "type": "coin" } },
  { "id": "22", "misol": "14*5+4+8", "javob": "82", "false1": "80", "false2": "77", "reward": { "amount": 22, "type": "coin" } },
  { "id": "23", "misol": "10*2+5+8", "javob": "33", "false1": "28", "false2": "43", "reward": { "amount": 27, "type": "coin" } },
  { "id": "24", "misol": "15*10+6+6", "javob": "162", "false1": "166", "false2": "167", "reward": { "amount": 25, "type": "coin" } },
  { "id": "25", "misol": "10*4+7+3", "javob": "50", "false1": "44", "false2": "54", "reward": { "amount": 27, "type": "coin" } },
  { "id": "26", "misol": "18*3+10+6", "javob": "70", "false1": "79", "false2": "65", "reward": { "amount": 19, "type": "coin" } },
  { "id": "27", "misol": "13*9+5+9", "javob": "131", "false1": "125", "false2": "129", "reward": { "amount": 40, "type": "coin" } },
  { "id": "28", "misol": "18*2+2+3", "javob": "41", "false1": "40", "false2": "42", "reward": { "amount": 34, "type": "coin" } },
  { "id": "29", "misol": "10*5+6+1", "javob": "57", "false1": "53", "false2": "61", "reward": { "amount": 17, "type": "coin" } },
  { "id": "30", "misol": "17*2+11+6", "javob": "51", "false1": "41", "false2": "53", "reward": { "amount": 32, "type": "coin" } },
  { "id": "31", "misol": "6*5+11+4", "javob": "45", "false1": "55", "false2": "39", "reward": { "amount": 28, "type": "coin" } },
  { "id": "32", "misol": "16*10+3+2", "javob": "165", "false1": "159", "false2": "172", "reward": { "amount": 27, "type": "coin" } },
  { "id": "33", "misol": "13*6+9+4", "javob": "91", "false1": "93", "false2": "94", "reward": { "amount": 36, "type": "coin" } },
  { "id": "34", "misol": "18*7+14+10", "javob": "150", "false1": "160", "false2": "147", "reward": { "amount": 48, "type": "coin" } },
  { "id": "35", "misol": "13*3+3+8", "javob": "50", "false1": "48", "false2": "45", "reward": { "amount": 48, "type": "coin" } },
  { "id": "36", "misol": "17*4+9+9", "javob": "86", "false1": "95", "false2": "87", "reward": { "amount": 44, "type": "coin" } },
  { "id": "37", "misol": "10*6+6+2", "javob": "98", "false1": "76", "false2": "66", "reward": { "amount": 229, "type": "coin" } },
  { "id": "38", "misol": "6*8+7+6", "javob": "61", "false1": "63", "false2": "62", "reward": { "amount": 39, "type": "coin" } },
  { "id": "39", "misol": "13*9+2+8", "javob": "127", "false1": "117", "false2": "136", "reward": { "amount": 31, "type": "coin" } },
  { "id": "40", "misol": "19*3+10+10", "javob": "77", "false1": "67", "false2": "75", "reward": { "amount": 26, "type": "coin" } },
  { "id": "41", "misol": "19*10+4+3", "javob": "197", "false1": "189", "false2": "198", "reward": { "amount": 42, "type": "coin" } },
  { "id": "42", "misol": "15*7+13+9", "javob": "127", "false1": "131", "false2": "121", "reward": { "amount": 13, "type": "coin" } },
  { "id": "43", "misol": "15*7+11+7", "javob": "123", "false1": "129", "false2": "124", "reward": { "amount": 18, "type": "coin" } },
  { "id": "44", "misol": "10*5+2+10", "javob": "62", "false1": "65", "false2": "52", "reward": { "amount": 13, "type": "coin" } },
  { "id": "45", "misol": "8*4+12+4", "javob": "48", "false1": "42", "false2": "50", "reward": { "amount": 29, "type": "coin" } },
  { "id": "46", "misol": "15*9+13+2", "javob": "150", "false1": "147", "false2": "157", "reward": { "amount": 32, "type": "coin" } },
  { "id": "47", "misol": "12*9+10+1", "javob": "119", "false1": "123", "false2": "127", "reward": { "amount": 51, "type": "coin" } },
  { "id": "48", "misol": "11*7+5+6", "javob": "88", "false1": "78", "false2": "92", "reward": { "amount": 24, "type": "coin" } },
  { "id": "49", "misol": "17*10+1+9", "javob": "180", "false1": "177", "false2": "175", "reward": { "amount": 33, "type": "coin" } },
  { "id": "50", "misol": "13*5+8+6", "javob": "99", "false1": "89", "false2": "76", "reward": { "amount": 154, "type": "coin" } }
]
